Punjabi_Stemmer/__init__.py
Punjabi_Stemmer/stemmer.py
punjabi_stemmer-1.0.1.dist-info/LICENSE.txt
punjabi_stemmer-1.0.1.dist-info/METADATA
punjabi_stemmer-1.0.1.dist-info/WHEEL
punjabi_stemmer-1.0.1.dist-info/top_level.txt
punjabi_stemmer-1.0.1.dist-info/RECORD
