Metadata-Version: 2.1
Name: punjabi-stemmer
Version: 1.0.1
Summary: A Python library for stemming Punjabi language words, including preprocessing for noise removal.
Home-page: https://github.com/gurpejsingh13/Punjabi_Stemmer.git
Author: Gurpej Singh
Author-email: gurpejsingh462@gmail.com
License: MIT
Keywords: stemmer,punjabi,nlp,punjabi language,Gurmukhi Language,natural language processing,text processing,noise removal,Stemming,Brute Force Algorithm,Suffix Striping,Under-stemming,Over-stemming,Stemming Algorithm
Platform: UNKNOWN
Classifier: Development Status :: 5 - Production/Stable
Classifier: Intended Audience :: Developers
Classifier: Topic :: Software Development :: Libraries :: Python Modules
Classifier: License :: OSI Approved :: MIT License
Classifier: Programming Language :: Python :: 3
Classifier: Programming Language :: Python :: 3.7
Classifier: Programming Language :: Python :: 3.8
Classifier: Programming Language :: Python :: 3.9
Classifier: Programming Language :: Python :: 3.10
Requires-Python: >=3.7
